{"data":{"properties":{"name":{"name":"name","reference":"scalar","unique":true,"getter":false,"setter":false,"type":"string","array":false},"biography":{"name":"biography","reference":"scalar","nullable":true,"getter":false,"setter":false,"type":"string","array":false,"optional":true},"country":{"name":"country","reference":"scalar","nullable":true,"getter":false,"setter":false,"type":"string","array":false,"optional":true},"perfumeDesigners":{"name":"perfumeDesigners","reference":"1:m","cascade":["persist"],"type":"PerfumeDesigner","array":false}},"primaryKeys":[],"filters":{},"hooks":{},"indexes":[],"uniques":[],"className":"Designer","path":"./src/entities/Designer.ts","name":"Designer","abstract":false,"constructorParams":["name","biography","country"],"toJsonParams":[],"extends":"BaseEntity","useCache":true,"collection":"designer"},"origin":"./src/entities/Designer.ts","hash":"4d481a299140d49d6579c4823504591e","version":"5.9.8"}
